code_profilers/__init__.py
code_profilers/decorators.py
code_profilers/logger.py
code_profilers/main_profiler.py
code_profilers/settings.py
code_profilers/version.py
code_profilers/integrations/__init__.py
code_profilers/integrations/django/__init__.py
code_profilers/integrations/django/middlewares.py
code_profilers/integrations/flask/__init__.py
code_profilers/profilers/__init__.py
code_profilers/profilers/base/__init__.py
code_profilers/profilers/base/profiler.py
code_profilers/profilers/mysql/__init__.py
code_profilers/profilers/mysql/profiler.py
code_profilers/profilers/mysql/reporter.py
code_profilers/profilers/mysql/settings.py
code_profilers/profilers/postgresql/__init__.py
code_profilers/profilers/postgresql/profiler.py
code_profilers/profilers/postgresql/reporter.py
code_profilers/profilers/postgresql/settings.py
code_profilers-1.3.1.dist-info/licenses/LICENSE
code_profilers-1.3.1.dist-info/METADATA
code_profilers-1.3.1.dist-info/WHEEL
code_profilers-1.3.1.dist-info/top_level.txt
code_profilers-1.3.1.dist-info/RECORD
