Metadata-Version: 2.4
Name: code_profilers
Version: 1.3.1
Summary: # Introduction
Home-page: https://github.com/Code-Profilers/base
Author: Hady Eslam
Author-email: abdoaslam000@gmail.com
Keywords: python,profilers,profiler
License-File: LICENSE
Dynamic: author
Dynamic: author-email
Dynamic: description
Dynamic: description-content-type
Dynamic: home-page
Dynamic: keywords
Dynamic: license-file
Dynamic: summary
